ALU/ALU32.v
module ALU32(
op,in0,in1,
carryout,overflow,zero,out
    );
    //carryout:进位/借位
    input [31:0] in0,in1;
    input [10:0] op;
    output reg[31:0] out;
    output reg carryout,overflow,zero;//进位/溢出/0
   
always@(*)
begin
    case(op)
        //add
        11'b00000100000:
            begin
            out=in0+in1;
            //溢出的两种必要条件：1.正数加正数 2.负数加负数
            overflow=((in0[31]==in1[31])&&(~out[31]==in0[31]))?1:0;
            zero=(out==0)?1:0;
            carryout=0;
            end
        //addu
        11'b00000100001:
            begin
            //carryout承担进位
            {carryout,out}=in0+in1;
            zero=(out==0)?1:0;
            overflow=0;
            end
        //sub
        11'b00000100010:
            begin
            out=in0-in1;
            //两种情况：正-负=负（上溢）负-正=正（下溢）
            overflow=((in0[31]==0&&in1[31]==1&&out[31]==1)||(in0[31]==1&&in1[31]==0&&out[31]==0))?1:0;
            zero=(in0==in1)?1:0;
            carryout=0;
            end
        //subu
        11'b00000100011:
            begin
            {carryout,out}=in0-in1;
            zero=(out==0)?1:0;
            overflow=0;
            end
        //and
        11'b00000100100:
            begin
            out=in0&in1;
            zero=(out==0)?1:0;
            carryout=0;
            overflow=0;
            end
        //or
        11'b00000100101:
            begin
            out=in0|in1;
            zero=(out==0)?1:0;
            carryout=0;
            overflow=0;
            end
        //xor
        11'b00000100110:
            begin
            out=in0^in1;
            zero=(out==0)?1:0;
            carryout=0;
            overflow=0;
            end
        //nor
        11'b00000100111:
            begin
            out=~(in0|in1);
            zero=(out==0)?1:0;
            carryout=0;
            overflow=0;
            end
        //slt
        11'b00000101010:
            begin                        
            if(in0[31]==1&&in1[31]==0)
                out=1;
            else if(in0[31]==0&&in1[31]==1)
                out=0;
            else 
                out=(in0<in1)?1:0;
           overflow=out; 
           zero=(out==0)?1:0;
           carryout=0;              
           end
        //sltu
        11'b00000101011:
            begin
                out=(in0<in1)?1:0;
                carryout=out;
                zero=(out==0)?1:0;
                overflow=0;
            end
        //shl
        11'b00000000100:
            begin
                {carryout,out}=in0<<in1;
                overflow=0;
                zero=(out==0)?1:0;
            end
        //shr
        11'b00000000110:
            begin
                out=in0>>in1;
                carryout=in0[in1-1];
                overflow=0;
                zero=(out==0)?1:0;
            end
        //sar
        11'b00000000111:
            begin
                out=($signed(in0))>>>in1;
                carryout=in0[in1-1];
                overflow=0;
                zero=(out==0)?1:0;
            end
        //sal
        11'b00000001000:
            begin
                {carryout,out}=($signed(in0))<<<in1;
                overflow=0;
                zero=(out==0)?1:0;
            end
    endcase
end
endmodule

ALU/ALU32_test.v
module ALU32_test(

    );
    reg [10:0] op;
    reg [31:0] in0,in1;
    wire [31:0] out;
    wire carryout,overflow,zero;
    ALU32 alu(op,in0,in1,carryout,overflow,zero,out);
    initial
    begin
    //add
         op=11'b00000100000;        
         in0=32'hf2340000;
         in1=32'h80000000;
    #20  in0=32'h7fffffff;
         in1=32'h70000001;
    #20  in0=32'h7fffffff;
         in1=32'hf0000001;
    #20  in0=32'hffffffff;
         in1=32'h00000001;
    //addu          
    #20  op=11'b00000100001;   
         in0=32'hf2340000;
         in1=32'h80000000;
    #20  in0=32'h7fffffff;
         in1=32'h70000001;
    #20  in0=32'hffffffff;
         in1=32'h00000001;
    //sub    
    #20  op=11'b00000100010;        
         in0=32'h72340000;
         in1=32'h60000000;
    #20  in0=32'h7fffffff;
         in1=32'hf0000001;
    #20  in0=32'hf00fffff;
         in1=32'h7ffffff1;
    #20  in0=32'hffffffff;
         in1=32'hffffffff;
    #20  in0=32'hf0000000;
         in1=32'h0fffffff; 
    //subu
    #20  op=11'b00000100011;        
         in0=32'h72340000;
         in1=32'h60000000;
    #20  in0=32'h7fffffff;
         in1=32'hf0000001;
    #20  in0=32'hffffffff;
         in1=32'hffffffff;
    #20  in0=32'hf0000000;
         in1=32'h0fffffff; 
    //and
    #20  op=11'b00000100100;        
         in0=32'h72340000;
         in1=32'h60000000;
    #20  in0=32'h7fffffff;
         in1=32'h00000000; 
    //or
    #20  op=11'b00000100101;        
         in0=32'h00000000;
         in1=32'h00000000;
    #20  in0=32'h7fffffff;
         in1=32'hf0000001;
    //xor
    #20  op=11'b00000100110;        
         in0=32'ha0000000;
         in1=32'h50000000;
    #20  in0=32'h7fffffff;
         in1=32'hf0000001;
    //nor
    #20  op=11'b00000100111;        
         in0=32'h123451ff;
         in1=32'h60000000;
    #20  in0=32'h7fffffff;
         in1=32'hf0000001;
    //slt
    #20  op=11'b00000101010;        
         in0=32'h72340000;
         in1=32'hf0000000;
    #20  in0=32'h7000000f;
         in1=32'h7f000001;
    #20  in0=32'hf0001231;
         in1=32'h7ac34545;
    //sltu
    #20  op=11'b00000101011;        
         in0=32'h72340000;
         in1=32'hf0000000;
    #20  in0=32'h7000000f;
         in1=32'h7f000001;
    #20  in0=32'hf0001231;
         in1=32'h7ac34545;
    //shl
    #20  op=11'b00000000100;
         in0=32'hffffffff;
         in1=32'd5;
    //shr
    #20  op=11'b00000000110;
         in0=32'hffffffff;
         in1=32'd5;
    //sar
    #20  op=11'b00000000111;
         in0=32'hffffffff;
         in1=32'd3;
    #20  in0=32'h0fffffff;
         in1=32'd5;
    end

initial
begin
   $dumpfile("ALU32.vcd");
   $dumpvars(0,ALU32_test);
end
endmodule

ALU/ALU32.vcd
$date
	Sun Oct 16 15:03:54 2022
$end
$version
	Icarus Verilog
$end
$timescale
	1s
$end
$scope module ALU32_test $end
$var wire 1 ! zero $end
$var wire 1 " overflow $end
$var wire 32 # out [31:0] $end
$var wire 1 $ carryout $end
$var reg 32 % in0 [31:0] $end
$var reg 32 & in1 [31:0] $end
$var reg 11 ' op [10:0] $end
$scope module alu $end
$var wire 32 ( in0 [31:0] $end
$var wire 32 ) in1 [31:0] $end
$var wire 11 * op [10:0] $end
$var reg 1 $ carryout $end
$var reg 32 + out [31:0] $end
$var reg 1 " overflow $end
$var reg 1 ! zero $end
$upscope $end
$upscope $end
$enddefinitions $end
#0
$dumpvars
b1110010001101000000000000000000 +
b100000 *
b10000000000000000000000000000000 )
b11110010001101000000000000000000 (
b100000 '
b10000000000000000000000000000000 &
b11110010001101000000000000000000 %
0$
b1110010001101000000000000000000 #
1"
0!
$end
#20
b11110000000000000000000000000000 #
b11110000000000000000000000000000 +
b1110000000000000000000000000001 &
b1110000000000000000000000000001 )
b1111111111111111111111111111111 %
b1111111111111111111111111111111 (
#40
0"
b1110000000000000000000000000000 #
b1110000000000000000000000000000 +
b11110000000000000000000000000001 &
b11110000000000000000000000000001 )
#60
1!
b0 #
b0 +
b1 &
b1 )
b11111111111111111111111111111111 %
b11111111111111111111111111111111 (
#80
0!
1$
b1110010001101000000000000000000 #
b1110010001101000000000000000000 +
b10000000000000000000000000000000 &
b10000000000000000000000000000000 )
b11110010001101000000000000000000 %
b11110010001101000000000000000000 (
b100001 '
b100001 *
#100
0$
b11110000000000000000000000000000 #
b11110000000000000000000000000000 +
b1110000000000000000000000000001 &
b1110000000000000000000000000001 )
b1111111111111111111111111111111 %
b1111111111111111111111111111111 (
#120
1!
1$
b0 #
b0 +
b1 &
b1 )
b11111111111111111111111111111111 %
b11111111111111111111111111111111 (
#140
0$
0!
b10010001101000000000000000000 #
b10010001101000000000000000000 +
b1100000000000000000000000000000 &
b1100000000000000000000000000000 )
b1110010001101000000000000000000 %
b1110010001101000000000000000000 (
b100010 '
b100010 *
#160
1"
b10001111111111111111111111111110 #
b10001111111111111111111111111110 +
b11110000000000000000000000000001 &
b11110000000000000000000000000001 )
b1111111111111111111111111111111 %
b1111111111111111111111111111111 (
#180
b1110000000100000000000000001110 #
b1110000000100000000000000001110 +
b1111111111111111111111111110001 &
b1111111111111111111111111110001 )
b11110000000011111111111111111111 %
b11110000000011111111111111111111 (
#200
1!
0"
b0 #
b0 +
b11111111111111111111111111111111 &
b11111111111111111111111111111111 )
b11111111111111111111111111111111 %
b11111111111111111111111111111111 (
#220
0!
b11100000000000000000000000000001 #
b11100000000000000000000000000001 +
b1111111111111111111111111111 &
b1111111111111111111111111111 )
b11110000000000000000000000000000 %
b11110000000000000000000000000000 (
#240
b10010001101000000000000000000 #
b10010001101000000000000000000 +
b1100000000000000000000000000000 &
b1100000000000000000000000000000 )
b1110010001101000000000000000000 %
b1110010001101000000000000000000 (
b100011 '
b100011 *
#260
1$
b10001111111111111111111111111110 #
b10001111111111111111111111111110 +
b11110000000000000000000000000001 &
b11110000000000000000000000000001 )
b1111111111111111111111111111111 %
b1111111111111111111111111111111 (
#280
1!
0$
b0 #
b0 +
b11111111111111111111111111111111 &
b11111111111111111111111111111111 )
b11111111111111111111111111111111 %
b11111111111111111111111111111111 (
#300
0!
b11100000000000000000000000000001 #
b11100000000000000000000000000001 +
b1111111111111111111111111111 &
b1111111111111111111111111111 )
b11110000000000000000000000000000 %
b11110000000000000000000000000000 (
#320
b1100000000000000000000000000000 #
b1100000000000000000000000000000 +
b1100000000000000000000000000000 &
b1100000000000000000000000000000 )
b1110010001101000000000000000000 %
b1110010001101000000000000000000 (
b100100 '
b100100 *
#340
1!
b0 #
b0 +
b0 &
b0 )
b1111111111111111111111111111111 %
b1111111111111111111111111111111 (
#360
b0 %
b0 (
b100101 '
b100101 *
#380
0!
b11111111111111111111111111111111 #
b11111111111111111111111111111111 +
b11110000000000000000000000000001 &
b11110000000000000000000000000001 )
b1111111111111111111111111111111 %
b1111111111111111111111111111111 (
#400
b11110000000000000000000000000000 #
b11110000000000000000000000000000 +
b1010000000000000000000000000000 &
b1010000000000000000000000000000 )
b10100000000000000000000000000000 %
b10100000000000000000000000000000 (
b100110 '
b100110 *
#420
b10001111111111111111111111111110 #
b10001111111111111111111111111110 +
b11110000000000000000000000000001 &
b11110000000000000000000000000001 )
b1111111111111111111111111111111 %
b1111111111111111111111111111111 (
#440
b10001101110010111010111000000000 #
b10001101110010111010111000000000 +
b1100000000000000000000000000000 &
b1100000000000000000000000000000 )
b10010001101000101000111111111 %
b10010001101000101000111111111 (
b100111 '
b100111 *
#460
1!
b0 #
b0 +
b11110000000000000000000000000001 &
b11110000000000000000000000000001 )
b1111111111111111111111111111111 %
b1111111111111111111111111111111 (
#480
b11110000000000000000000000000000 &
b11110000000000000000000000000000 )
b1110010001101000000000000000000 %
b1110010001101000000000000000000 (
b101010 '
b101010 *
#500
0!
1"
b1 #
b1 +
b1111111000000000000000000000001 &
b1111111000000000000000000000001 )
b1110000000000000000000000001111 %
b1110000000000000000000000001111 (
#520
b1111010110000110100010101000101 &
b1111010110000110100010101000101 )
b11110000000000000001001000110001 %
b11110000000000000001001000110001 (
#540
0"
1$
b11110000000000000000000000000000 &
b11110000000000000000000000000000 )
b1110010001101000000000000000000 %
b1110010001101000000000000000000 (
b101011 '
b101011 *
#560
b1111111000000000000000000000001 &
b1111111000000000000000000000001 )
b1110000000000000000000000001111 %
b1110000000000000000000000001111 (
#580
1!
0$
b0 #
b0 +
b1111010110000110100010101000101 &
b1111010110000110100010101000101 )
b11110000000000000001001000110001 %
b11110000000000000001001000110001 (
#600
0!
1$
b11111111111111111111111111100000 #
b11111111111111111111111111100000 +
b101 &
b101 )
b11111111111111111111111111111111 %
b11111111111111111111111111111111 (
b100 '
b100 *
#620
b111111111111111111111111111 #
b111111111111111111111111111 +
b110 '
b110 *
#640
b11111111111111111111111111111111 #
b11111111111111111111111111111111 +
b11 &
b11 )
b111 '
b111 *
#660
b11111111111111111111111 #
b11111111111111111111111 +
b101 &
b101 )
b1111111111111111111111111111 %
b1111111111111111111111111111 (
